qiwi_handler/__init__.py
qiwi_handler/client.py
qiwi_handler/exceptions.py
qiwi_handler/account_api/__init__.py
qiwi_handler/account_api/history.py
qiwi_handler/account_api/profile.py
qiwi_handler/handler/__init__.py
qiwi_handler/handler/check_pay.py
qiwi_handler/handler/run.py
qiwi_handler/loader/__init__.py
qiwi_handler/loader/do_request.py
qiwi_handler/loader/converter/__init__.py
qiwi_handler/loader/converter/converter_history.py
qiwi_handler/loader/converter/converter_profile.py
qiwi_handler/samples/__init__.py
qiwi_handler/samples/run.py
qiwi_handler/samples/checkPay/__init__.py
qiwi_handler/types/__init__.py
qiwi_handler/types/history.py
qiwi_handler/types/balance/__init__.py
qiwi_handler/types/identification/__init__.py
qiwi_handler/types/limits/__init__.py
qiwi_handler/types/profile/__init__.py
qiwi_handler/types/profile/auth_info.py
qiwi_handler/types/profile/contract_info.py
qiwi_handler/types/profile/mobile_pin_info.py
qiwi_handler/types/profile/pass_info.py
qiwi_handler/types/profile/pin_info.py
qiwi_handler/types/profile/user_info.py
qiwi_handler/types/transaction/__init__.py
qiwi_handler/types/transaction/commission.py
qiwi_handler/types/transaction/extras.py
qiwi_handler/types/transaction/provider.py
qiwi_handler/types/transaction/source.py
qiwi_handler/types/transaction/sum.py
qiwi_handler/types/transaction/total.py
qiwi_handler/utils/__init__.py
qiwi_handler/utils/datetimes_utils.py
qiwi_handler/utils/methods.py
qiwi_handler-0.3.0.dist-info/LICENSE
qiwi_handler-0.3.0.dist-info/METADATA
qiwi_handler-0.3.0.dist-info/WHEEL
qiwi_handler-0.3.0.dist-info/top_level.txt
qiwi_handler-0.3.0.dist-info/RECORD
