Metadata-Version: 2.1
Name: qiwi-handler
Version: 0.3.0
Summary: Обертка с обработчиком для qiwi
Home-page: https://github.com/bezumnui/qiwi_handler/
Author: bezumnui
Author-email: bezumnui.mistikgt@gmail.com
License: UNKNOWN
Project-URL: Bug Tracker, https://github.com/bezumnui/qiwi_handler/issues
Project-URL: Get Qiwi Token, https://qiwi.com/api
Platform: UNKNOWN
Classifier: Programming Language :: Python :: 3
Classifier: License :: OSI Approved :: MIT License
Classifier: Operating System :: OS Independent
Requires-Python: >=3.6
License-File: LICENSE
